Workbook

Sheet Arithmatic Functions
M2: Descriptive Analysis
M3: Total Salary | N3: =SUM(J6:J43) -> 2191000
M4: Average Salary | N4: =AVERAGE(J6:J43) -> 57657.895
B5: C_Code | C5: FirstName | D5: LastName | E5: Birthdate | F5: Gender | G5: M_Status | H5: Department | I5: Region | J5: Basic Salary | M5: Total Employees | N5: =COUNTA(C6:C43) -> 38
B6: 150834 | C6: Ram | D6: Ambradkar | E6: 31199 | F6: Female | G6: Married | H6: FLM | I6: North | J6: 48000 | M6: Max Salary | N6: =MAX(J6:J43) -> 92000
B7: 150784 | C7: Sachin | D7: Bangera | E7: 28365 | F7: Female | G7: Single | H7: Digital Marketing | I7: North | J7: 35000 | M7: Min Salary | N7: =MIN(J6:J43) -> 15000
B8: 150791 | C8: Rajesh | D8: Bohra | E8: 23346 | F8: Female | G8: Married | H8: Digital Marketing | I8: North | J8: 67000
B9: 150940 | C9: Rajeesh | D9: C | E9: 26906 | F9: Male | G9: Single | H9: Inside Sales | I9: South | J9: 87000 | M9: More Analysis
B10: 150777 | C10: Melwyn | D10: Crasto | E10: 21123 | F10: Male | G10: Married | H10: Marketing | I10: North | J10: 22000 | M10: Total number Employees working in North | N10: =COUNTIF(I6:I43,I6) -> 10
B11: 150805 | C11: Rajesh | D11: Dedhia | E11: 26172 | F11: Male | G11: Married | H11: Director | I11: North | J11: 91000 | M11: Average Salary Paid to Sales Departement of North Region | N11: =AVERAGEIFS(J6:J43,H6:H43,H37,I6:I43,I6) -> 52000
B12: 150990 | C12: Dattatray | D12: Desai | E12: 36400 | F12: Male | G12: Married | H12: Learning & Development | I12: Mid West | J12: 77000 | M12: Max Salary paid in Digital Marketing | N12: =_xlfn.MAXIFS(J6:J43,H6:H43,H7) -> 92000
B13: 150989 | C13: Vishnu | D13: Desai | E13: 33113 | F13: Male | G13: Married | H13: Digital Marketing | I13: Mid West | J13: 45000
B14: 150881 | C14: Dinesh | D14: Dhanuka | E14: 30337 | F14: Male | G14: Single | H14: Digital Marketing | I14: East | J14: 92000
B15: 150814 | C15: Heena | D15: Dongre | E15: 26246 | F15: Male | G15: Married | H15: Inside Sales | I15: North | J15: 50000
B16: 150937 | C16: Dhiren | D16: Haria | E16: 24700 | F16: Male | G16: Married | H16: Learning & Development | I16: South | J16: 37000
B17: 150888 | C17: Gururaj | D17: Joshi | E17: 29221 | F17: Male | G17: Married | H17: Learning & Development | I17: East | J17: 43000 | M17: Find out the sum of Basic Salary for FLM Department and North Region
B18: 150865 | C18: Ruffina | D18: Joshi | E18: 31279 | F18: Female | G18: Married | H18: CEO | I18: East | J18: 90000
B19: 150858 | C19: Jagjit | D19: Kahlon | E19: 34846 | F19: Male | G19: Married | H19: CCD | I19: East | J19: 34000 | M19: Regionwise Departmentwise Salary Report
B20: 150930 | C20: Piyush | D20: Kamdar | E20: 37027 | F20: Male | G20: Married | H20: Digital Marketing | I20: South | J20: 82000 | M20: Department/Region | N20: North
B21: 150894 | C21: D | D21: Kulkarni | E21: 37124 | F21: Male | G21: Married | H21: Inside Sales | I21: South | J21: 67000 | M21: FLM | N21: =SUMIFS(J6:J43,H6:H43,H6,I6:I43,I15) -> 48000
B22: 150947 | C22: Raju | D22: Manek | E22: 33449 | F22: Female | G22: Married | H22: CCD | I22: South | J22: 85000
B23: 150905 | C23: Yogesh | D23: Mansharamani | E23: 30819 | F23: Female | G23: Single | H23: FLM | I23: South | J23: 62000
B24: 150995 | C24: Satish | D24: Pasari | E24: 35330 | F24: Male | G24: Married | H24: Inside Sales | I24: Mid West | J24: 15000
B25: 150912 | C25: Nitin | D25: Patki | E25: 37629 | F25: Female | G25: Married | H25: Operations | I25: South | J25: 81000
B26: 150921 | C26: Prem | D26: Pherwani | E26: 38092 | F26: Male | G26: Married | H26: Finance | I26: South | J26: 19000
B27: 150851 | C27: Sudesh | D27: Pillai | E27: 29368 | F27: Male | G27: Single | H27: Inside Sales | I27: East | J27: 75000
B28: 150867 | C28: Boneca | D28: Rego | E28: 29028 | F28: Female | G28: Single | H28: Finance | I28: East | J28: 49000
B29: 150899 | C29: Sharadchandra | D29: Riswadkar | E29: 37400 | F29: Male | G29: Married | H29: CCD | I29: South | J29: 50000
B30: 150975 | C30: Simon | D30: Rodrigues | E30: 31478 | F30: Male | G30: Married | H30: Finance | I30: Mid West | J30: 83000
B31: 150901 | C31: Ashok | D31: Samtaney | E31: 32946 | F31: Female | G31: Married | H31: Sales | I31: South | J31: 53000
B32: 150968 | C32: Praful | D32: Savla | E32: 37208 | F32: Male | G32: Married | H32: Operations | I32: South | J32: 65000
B33: 150773 | C33: Stan | D33: Serrao | E33: 26860 | F33: Male | G33: Married | H33: Finance | I33: North | J33: 85000
... B43: 150821 | C43: Yashraj | D43: Vaidya | E43: 29966 | F43: Male | G43: Single | H43: CCD | I43: North | J43: 26000

Sheet Logical Functions
C1: Add new column for each task
B2: 1 | C2: Write 'Eligible for Gift', in front of Females having Salary less than 50000
B3: 2 | C3: Employees having Salary less than 30000 and belong to CCD department, Get 9000 as Bonus
B4: 3 | C4: Employees joined before 1980 , write them as 'Retired'
B5: 4 | C5: Employees belong to Sales or Marketing Department with Basic Salary < 45000 get Bonus of 25000
B6: 5 | C6: Gift everyone 1500 rs. Amazon Voucher, except Director and CEO
A9: C_Code | B9: FirstName | C9: LastName | D9: Joining Date | E9: Gender | F9: M_Status | G9: Department | H9: Basic Salary | I9: Region | J9: 1 | K9: 2 | L9: 3 | M9: 4 | N9: 5
A10: 150773 | B10: Stan | C10: Serrao | D10: 26860 | E10: Male | F10: Married | G10: Finance | H10: 85000 | I10: North | J10: =IF(AND(E10="Female",H10<50000),"Eligible for Gift","") | K10: =IF(AND(H10<30000,G10="CCD"),9000,"") | L10: =IF(YEAR(D10)<1980,"Retired","") -> Retired | M10: =IF(AND(OR(G10="Sales",G10="Marketing"),H10<45000),25000,"") | N10: =IF(OR(G10="Director",G10="CEO"),"",1500) -> 1500
A11: 150777 | B11: Melwyn | C11: Crasto | D11: 21123 | E11: Male | F11: Married | G11: Marketing | H11: 22000 | I11: North | J11: =IF(AND(E11="Female",H11<50000),"Eligible for Gift","") | K11: =IF(AND(H11<30000,G11="CCD"),9000,"") | L11: =IF(YEAR(D11)<1980,"Retired","") -> Retired | M11: =IF(AND(OR(G11="Sales",G11="Marketing"),H11<45000),25000,"") -> 25000 | N11: =IF(OR(G11="Director",G11="CEO"),"",1500) -> 1500
A12: 150784 | B12: Sachin | C12: Bangera | D12: 28365 | E12: Female | F12: Single | G12: Digital Marketing | H12: 35000 | I12: North | J12: =IF(AND(E12="Female",H12<50000),"Eligible for Gift","") -> Eligible for Gift | K12: =IF(AND(H12<30000,G12="CCD"),9000,"") | L12: =IF(YEAR(D12)<1980,"Retired","") -> Retired | M12: =IF(AND(OR(G12="Sales",G12="Marketing"),H12<45000),25000,"") | N12: =IF(OR(G12="Director",G12="CEO"),"",1500) -> 1500
A13: 150791 | B13: Rajesh | C13: Bohra | D13: 23346 | E13: Female | F13: Married | G13: Digital Marketing | H13: 67000 | I13: South | J13: =IF(AND(E13="Female",H13<50000),"Eligible for Gift","") | K13: =IF(AND(H13<30000,G13="CCD"),9000,"") | L13: =IF(YEAR(D13)<1980,"Retired","") -> Retired | M13: =IF(AND(OR(G13="Sales",G13="Marketing"),H13<45000),25000,"") | N13: =IF(OR(G13="Director",G13="CEO"),"",1500) -> 1500
A14: 150798 | B14: Tulsidas | C14: Shetty | D14: 28276 | E14: Female | F14: Married | G14: Digital Marketing | H14: 81000 | I14: North | J14: =IF(AND(E14="Female",H14<50000),"Eligible for Gift","") | K14: =IF(AND(H14<30000,G14="CCD"),9000,"") | L14: =IF(YEAR(D14)<1980,"Retired","") -> Retired | M14: =IF(AND(OR(G14="Sales",G14="Marketing"),H14<45000),25000,"") | N14: =IF(OR(G14="Director",G14="CEO"),"",1500) -> 1500
A15: 150805 | B15: Rajesh | C15: Dedhia | D15: 26172 | E15: Male | F15: Married | G15: Director | H15: 91000 | I15: North | J15: =IF(AND(E15="Female",H15<50000),"Eligible for Gift","") | K15: =IF(AND(H15<30000,G15="CCD"),9000,"") | L15: =IF(YEAR(D15)<1980,"Retired","") -> Retired | M15: =IF(AND(OR(G15="Sales",G15="Marketing"),H15<45000),25000,"") | N15: =IF(OR(G15="Director",G15="CEO"),"",1500)
A16: 150814 | B16: Heena | C16: Dongre | D16: 26246 | E16: Male | F16: Married | G16: Inside Sales | H16: 50000 | I16: Mid West | J16: =IF(AND(E16="Female",H16<50000),"Eligible for Gift","") | K16: =IF(AND(H16<30000,G16="CCD"),9000,"") | L16: =IF(YEAR(D16)<1980,"Retired","") -> Retired | M16: =IF(AND(OR(G16="Sales",G16="Marketing"),H16<45000),25000,"") | N16: =IF(OR(G16="Director",G16="CEO"),"",1500) -> 1500
A17: 150821 | B17: Yashraj | C17: Vaidya | D17: 29966 | E17: Male | F17: Single | G17: CCD | H17: 26000 | I17: Mid West | J17: =IF(AND(E17="Female",H17<50000),"Eligible for Gift","") | K17: =IF(AND(H17<30000,G17="CCD"),9000,"") -> 9000 | L17: =IF(YEAR(D17)<1980,"Retired","") | M17: =IF(AND(OR(G17="Sales",G17="Marketing"),H17<45000),25000,"") | N17: =IF(OR(G17="Director",G17="CEO"),"",1500) -> 1500
A18: 150830 | B18: Rajeev | C18: Singh | D18: 29037 | E18: Female | F18: Married | G18: Sales | H18: 52000 | I18: East | J18: =IF(AND(E18="Female",H18<50000),"Eligible for Gift","") | K18: =IF(AND(H18<30000,G18="CCD"),9000,"") | L18: =IF(YEAR(D18)<1980,"Retired","") -> Retired | M18: =IF(AND(OR(G18="Sales",G18="Marketing"),H18<45000),25000,"") | N18: =IF(OR(G18="Director",G18="CEO"),"",1500) -> 1500
A19: 150834 | B19: Ram | C19: Ambradkar | D19: 31199 | E19: Female | F19: Married | G19: FLM | H19: 48000 | I19: North | J19: =IF(AND(E19="Female",H19<50000),"Eligible for Gift","") -> Eligible for Gift | K19: =IF(AND(H19<30000,G19="CCD"),9000,"") | L19: =IF(YEAR(D19)<1980,"Retired","") | M19: =IF(AND(OR(G19="Sales",G19="Marketing"),H19<45000),25000,"") | N19: =IF(OR(G19="Director",G19="CEO"),"",1500) -> 1500
A20: 150840 | B20: Piyush | C20: Shah | D20: 23136 | E20: Female | F20: Married | G20: Inside Sales | H20: 20000 | I20: South | J20: =IF(AND(E20="Female",H20<50000),"Eligible for Gift","") -> Eligible for Gift | K20: =IF(AND(H20<30000,G20="CCD"),9000,"") | L20: =IF(YEAR(D20)<1980,"Retired","") -> Retired | M20: =IF(AND(OR(G20="Sales",G20="Marketing"),H20<45000),25000,"") | N20: =IF(OR(G20="Director",G20="CEO"),"",1500) -> 1500
A21: 150850 | B21: Dhiren | C21: Sheth | D21: 32027 | E21: Male | F21: Married | G21: CCD | H21: 47000 | I21: East | J21: =IF(AND(E21="Female",H21<50000),"Eligible for Gift","") | K21: =IF(AND(H21<30000,G21="CCD"),9000,"") | L21: =IF(YEAR(D21)<1980,"Retired","") | M21: =IF(AND(OR(G21="Sales",G21="Marketing"),H21<45000),25000,"") | N21: =IF(OR(G21="Director",G21="CEO"),"",1500) -> 1500
... A47: 150995 | B47: Satish | C47: Pasari | D47: 35330 | E47: Male | F47: Married | G47: Inside Sales | H47: 15000 | I47: North | J47: =IF(AND(E47="Female",H47<50000),"Eligible for Gift","") | K47: =IF(AND(H47<30000,G47="CCD"),9000,"") | L47: =IF(YEAR(D47)<1980,"Retired","") | M47: =IF(AND(OR(G47="Sales",G47="Marketing"),H47<45000),25000,"") | N47: =IF(OR(G47="Director",G47="CEO"),"",1500) -> 1500

Sheet Index&Match
C4: C_Code | D4: FirstName | E4: LastName | F4: Birthdate | G4: Gender | H4: M_Status | I4: Department | J4: Region | K4: Basic Salary
C5: 150834 | D5: Ram | E5: Ambradkar | F5: 31199 | G5: Female | H5: Married | I5: FLM | J5: North | K5: 48000
C6: 150784 | D6: Sachin | E6: Bangera | F6: 28365 | G6: Female | H6: Single | I6: Digital Marketing | J6: North | K6: 35000
C7: 150791 | D7: Rajesh | E7: Bohra | F7: 23346 | G7: Female | H7: Married | I7: Digital Marketing | J7: North | K7: 67000 | M7: Figure out who has the Max and Min Salary
C8: 150940 | D8: Rajeesh | E8: C | F8: 26906 | G8: Male | H8: Single | I8: Inside Sales | J8: South | K8: 87000
C9: 150777 | D9: Melwyn | E9: Crasto | F9: 21123 | G9: Male | H9: Married | I9: Marketing | J9: North | K9: 22000 | M9: Name of Employees, who have | O9: First Name
C10: 150805 | D10: Rajesh | E10: Dedhia | F10: 26172 | G10: Male | H10: Married | I10: Director | J10: North | K10: 91000 | M10: Max Salary | N10: =MAX(K5:K42) -> 92000 | O10: =INDEX(D5:D42,MATCH(MAX(K5:K42),K5:K42,0)) -> Dinesh
C11: 150990 | D11: Dattatray | E11: Desai | F11: 36400 | G11: Male | H11: Married | I11: Learning & Development | J11: Mid West | K11: 77000 | M11: Min Salary | N11: =MIN(K5:K42) -> 15000 | O11: =INDEX(D5:D42,MATCH(MIN(K5:K42),K5:K42,0)) -> Satish
C12: 150989 | D12: Vishnu | E12: Desai | F12: 33113 | G12: Male | H12: Married | I12: Digital Marketing | J12: Mid West | K12: 45000
C13: 150881 | D13: Dinesh | E13: Dhanuka | F13: 30337 | G13: Male | H13: Single | I13: Digital Marketing | J13: East | K13: 92000
C14: 150814 | D14: Heena | E14: Dongre | F14: 26246 | G14: Male | H14: Married | I14: Inside Sales | J14: North | K14: 50000
C15: 150937 | D15: Dhiren | E15: Haria | F15: 24700 | G15: Male | H15: Married | I15: Learning & Development | J15: South | K15: 37000
C16: 150888 | D16: Gururaj | E16: Joshi | F16: 29221 | G16: Male | H16: Married | I16: Learning & Development | J16: East | K16: 43000
C17: 150865 | D17: Ruffina | E17: Joshi | F17: 31279 | G17: Female | H17: Married | I17: CEO | J17: East | K17: 90000
C18: 150858 | D18: Jagjit | E18: Kahlon | F18: 34846 | G18: Male | H18: Married | I18: CCD | J18: East | K18: 34000
C19: 150930 | D19: Piyush | E19: Kamdar | F19: 37027 | G19: Male | H19: Married | I19: Digital Marketing | J19: South | K19: 82000
C20: 150894 | D20: D | E20: Kulkarni | F20: 37124 | G20: Male | H20: Married | I20: Inside Sales | J20: South | K20: 67000
C21: 150947 | D21: Raju | E21: Manek | F21: 33449 | G21: Female | H21: Married | I21: CCD | J21: South | K21: 85000
C22: 150905 | D22: Yogesh | E22: Mansharamani | F22: 30819 | G22: Female | H22: Single | I22: FLM | J22: South | K22: 62000
C23: 150995 | D23: Satish | E23: Pasari | F23: 35330 | G23: Male | H23: Married | I23: Inside Sales | J23: Mid West | K23: 15000
... C42: 150821 | D42: Yashraj | E42: Vaidya | F42: 29966 | G42: Male | H42: Single | I42: CCD | J42: North | K42: 26000

Sheet Master Emp sheet
D2: Get Region, Department and Salary of all Employees from Sheet "Source"
D3: If C-Code is not present, display "Retired"
D4: *Use Name Range and Vlookup with Match Function
C6: C_Code | D6: FirstName | E6: LastName | F6: Birthdate | G6: Gender | H6: M_Status | I6: Region | J6: Department | K6: Basic Salary
C7: 150834 | D7: Ram | E7: Ambradkar | F7: 31199 | G7: Female | H7: Married | I7: =IFERROR(VLOOKUP($C7,Source!$C$5:$F$40,MATCH(I$6,Source!C5:$F$5,0),FALSE),"retired") -> North | J7: =IFERROR(VLOOKUP($C7,Source!$C$5:$F$40,MATCH(J$6,Source!C5:$F$5,0),FALSE),"retired") -> FLM | K7: =IFERROR(VLOOKUP($C7,Source!$C$5:$F$40,MATCH(K$6,Source!C5:$F$5,0),FALSE),"retired") -> 48000
C8: 150784 | D8: Sachin | E8: Bangera | F8: 28365 | G8: Female | H8: Single | I8: =IFERROR(VLOOKUP($C8,Source!$C$5:$F$40,MATCH(I$6,Source!C$5:$F5,0),FALSE),"retired") -> North | J8: =IFERROR(VLOOKUP($C8,Source!$C$5:$F$40,MATCH(J$6,Source!C$5:$F6,0),FALSE),"retired") -> retired | K8: =IFERROR(VLOOKUP($C8,Source!$C$5:$F$40,MATCH(K$6,Source!C$5:$F6,0),FALSE),"retired") -> retired
C9: 150791 | D9: Rajesh | E9: Bohra | F9: 23346 | G9: Female | H9: Married | I9: =IFERROR(VLOOKUP($C9,Source!$C$5:$F$40,MATCH(I$6,Source!C$5:$F5,0),FALSE),"retired") -> North | J9: =IFERROR(VLOOKUP($C9,Source!$C$5:$F$40,MATCH(J$6,Source!C$5:$F7,0),FALSE),"retired") -> retired | K9: =IFERROR(VLOOKUP($C9,Source!$C$5:$F$40,MATCH(K$6,Source!C$5:$F7,0),FALSE),"retired") -> retired
C10: 150940 | D10: Rajeesh | E10: C | F10: 26906 | G10: Male | H10: Single | I10: =IFERROR(VLOOKUP($C10,Source!$C$5:$F$100,MATCH(I$6,Source!C$5:$F6,0),FALSE),"retired") -> retired | J10: =IFERROR(VLOOKUP($C10,Source!$C$5:$F$40,MATCH(J$6,Source!C$5:$F8,0),FALSE),"retired") -> retired | K10: =IFERROR(VLOOKUP($C10,Source!$C$5:$F$40,MATCH(K$6,Source!C$5:$F8,0),FALSE),"retired") -> retired
C11: 150777 | D11: Melwyn | E11: Crasto | F11: 21123 | G11: Male | H11: Married | I11: =IFERROR(VLOOKUP($C11,Source!$C$5:$F$100,MATCH(I$6,Source!C$5:$F7,0),FALSE),"retired") -> retired | J11: =IFERROR(VLOOKUP($C11,Source!$C$5:$F$40,MATCH(J$6,Source!C$5:$F9,0),FALSE),"retired") -> retired | K11: =IFERROR(VLOOKUP($C11,Source!$C$5:$F$40,MATCH(K$6,Source!C$5:$F9,0),FALSE),"retired") -> retired
C12: 150805 | D12: Rajesh | E12: Dedhia | F12: 26172 | G12: Male | H12: Married | I12: =IFERROR(VLOOKUP($C12,Source!$C$5:$F$100,MATCH(I$6,Source!C$5:$F8,0),FALSE),"retired") -> retired | J12: =IFERROR(VLOOKUP($C12,Source!$C$5:$F$40,MATCH(J$6,Source!C$5:$F10,0),FALSE),"retired") -> retired | K12: =IFERROR(VLOOKUP($C12,Source!$C$5:$F$40,MATCH(K$6,Source!C$5:$F10,0),FALSE),"retired") -> retired
C13: 150990 | D13: Dattatray | E13: Desai | F13: 36400 | G13: Male | H13: Married | I13: =IFERROR(VLOOKUP($C13,Source!$C$5:$F$100,MATCH(I$6,Source!C$5:$F9,0),FALSE),"retired") -> retired | J13: =IFERROR(VLOOKUP($C13,Source!$C$5:$F$40,MATCH(J$6,Source!C$5:$F11,0),FALSE),"retired") -> retired | K13: =IFERROR(VLOOKUP($C13,Source!$C$5:$F$40,MATCH(K$6,Source!C$5:$F11,0),FALSE),"retired") -> retired
C14: 150989 | D14: Vishnu | E14: Desai | F14: 33113 | G14: Male | H14: Married | I14: =IFERROR(VLOOKUP($C14,Source!$C$5:$F$100,MATCH(I$6,Source!C$5:$F10,0),FALSE),"retired") -> retired | J14: =IFERROR(VLOOKUP($C14,Source!$C$5:$F$40,MATCH(J$6,Source!C$5:$F12,0),FALSE),"retired") -> retired | K14: =IFERROR(VLOOKUP($C14,Source!$C$5:$F$40,MATCH(K$6,Source!C$5:$F12,0),FALSE),"retired") -> retired
C15: 150881 | D15: Dinesh | E15: Dhanuka | F15: 30337 | G15: Male | H15: Single | I15: =IFERROR(VLOOKUP($C15,Source!$C$5:$F$100,MATCH(I$6,Source!C$5:$F11,0),FALSE),"retired") -> retired | J15: =IFERROR(VLOOKUP($C15,Source!$C$5:$F$40,MATCH(J$6,Source!C$5:$F13,0),FALSE),"retired") -> retired | K15: =IFERROR(VLOOKUP($C15,Source!$C$5:$F$40,MATCH(K$6,Source!C$5:$F13,0),FALSE),"retired") -> retired
C16: 150814 | D16: Heena | E16: Dongre | F16: 26246 | G16: Male | H16: Married | I16: =IFERROR(VLOOKUP($C16,Source!$C$5:$F$100,MATCH(I$6,Source!C$5:$F12,0),FALSE),"retired") -> retired | J16: =IFERROR(VLOOKUP($C16,Source!$C$5:$F$40,MATCH(J$6,Source!C$5:$F14,0),FALSE),"retired") -> retired | K16: =IFERROR(VLOOKUP($C16,Source!$C$5:$F$40,MATCH(K$6,Source!C$5:$F14,0),FALSE),"retired") -> retired
C17: 150937 | D17: Dhiren | E17: Haria | F17: 24700 | G17: Male | H17: Married | I17: =IFERROR(VLOOKUP($C17,Source!$C$5:$F$100,MATCH(I$6,Source!C$5:$F13,0),FALSE),"retired") -> retired | J17: =IFERROR(VLOOKUP($C17,Source!$C$5:$F$40,MATCH(J$6,Source!C$5:$F15,0),FALSE),"retired") -> retired | K17: =IFERROR(VLOOKUP($C17,Source!$C$5:$F$40,MATCH(K$6,Source!C$5:$F15,0),FALSE),"retired") -> retired
C18: 150888 | D18: Gururaj | E18: Joshi | F18: 29221 | G18: Male | H18: Married | I18: =IFERROR(VLOOKUP($C18,Source!$C$5:$F$100,MATCH(I$6,Source!C$5:$F14,0),FALSE),"retired") -> retired | J18: =IFERROR(VLOOKUP($C18,Source!$C$5:$F$40,MATCH(J$6,Source!C$5:$F16,0),FALSE),"retired") -> retired | K18: =IFERROR(VLOOKUP($C18,Source!$C$5:$F$40,MATCH(K$6,Source!C$5:$F16,0),FALSE),"retired") -> retired
C19: 150865 | D19: Ruffina | E19: Joshi | F19: 31279 | G19: Female | H19: Married | I19: =IFERROR(VLOOKUP($C19,Source!$C$5:$F$100,MATCH(I$6,Source!C$5:$F15,0),FALSE),"retired") -> retired | J19: =IFERROR(VLOOKUP($C19,Source!$C$5:$F$40,MATCH(J$6,Source!C$5:$F17,0),FALSE),"retired") -> retired | K19: =IFERROR(VLOOKUP($C19,Source!$C$5:$F$40,MATCH(K$6,Source!C$5:$F17,0),FALSE),"retired") -> retired
C20: 150858 | D20: Jagjit | E20: Kahlon | F20: 34846 | G20: Male | H20: Married | I20: =IFERROR(VLOOKUP($C20,Source!$C$5:$F$100,MATCH(I$6,Source!C$5:$F16,0),FALSE),"retired") -> retired | J20: =IFERROR(VLOOKUP($C20,Source!$C$5:$F$40,MATCH(J$6,Source!C$5:$F18,0),FALSE),"retired") -> retired | K20: =IFERROR(VLOOKUP($C20,Source!$C$5:$F$40,MATCH(K$6,Source!C$5:$F18,0),FALSE),"retired") -> retired
C21: 150930 | D21: Piyush | E21: Kamdar | F21: 37027 | G21: Male | H21: Married | I21: =IFERROR(VLOOKUP($C21,Source!$C$5:$F$100,MATCH(I$6,Source!C$5:$F17,0),FALSE),"retired") -> retired | J21: =IFERROR(VLOOKUP($C21,Source!$C$5:$F$40,MATCH(J$6,Source!C$5:$F19,0),FALSE),"retired") -> retired | K21: =IFERROR(VLOOKUP($C21,Source!$C$5:$F$40,MATCH(K$6,Source!C$5:$F19,0),FALSE),"retired") -> retired
... C44: 150821 | D44: Yashraj | E44: Vaidya | F44: 29966 | G44: Male | H44: Single | I44: =IFERROR(VLOOKUP($C44,Source!$C$5:$F$100,MATCH(I$6,Source!C$5:$F40,0),FALSE),"retired") -> retired | J44: =IFERROR(VLOOKUP($C44,Source!$C$5:$F$40,MATCH(J$6,Source!C$5:$F42,0),FALSE),"retired") -> retired | K44: =IFERROR(VLOOKUP($C44,Source!$C$5:$F$40,MATCH(K$6,Source!C$5:$F42,0),FALSE),"retired") -> retired

Sheet Source
C5: SorceData | D5: Department | E5: Region | F5: Basic Salary
C6: 150773 | D6: Finance | E6: North | F6: 85000
C7: 150777 | D7: Marketing | E7: North | F7: 22000
C8: 150784 | D8: Digital Marketing | E8: North | F8: 35000
C9: 150791 | D9: Digital Marketing | E9: North | F9: 67000
C10: 150798 | D10: Digital Marketing | E10: North | F10: 81000
C11: 150805 | D11: Director | E11: North | F11: 91000
C12: 150814 | D12: Inside Sales | E12: North | F12: 50000
C13: 150821 | D13: CCD | E13: North | F13: 26000
C14: 150830 | D14: Sales | E14: North | F14: 52000
C15: 150834 | D15: FLM | E15: North | F15: 48000
C16: 150840 | D16: Inside Sales | E16: East | F16: 20000
C17: 150850 | D17: CCD | E17: East | F17: 47000
... C40: 150995 | D40: Inside Sales | E40: Mid West | F40: 15000

Sheet Date2
B3: Current Date | C3: =NOW() -> 46271.865
B4: Current Time | C4: =NOW() -> 46271.865
B6: Name | C6: Birthdate | D6: Day(in Number) | E6: Month(in number) | F6: Month(in text) | G6: Year | H6: Age(in years) | I6: Exact Age with Years,Month,days
B7: Boneca Rego | C7: 36478 | D7: =DAY(C7) -> 14 | E7: =MONTH(C7) -> 11 | F7: =TEXT(C7,"mmmm") -> November | G7: =YEAR(C7) -> 1999 | H7: =DATEDIF(C7,$C$3,"Y") -> 26 | I7: =DATEDIF(C7,$C$3,"Y")&"Years,"&DATEDIF(C7,$C$3,"YM")&"Months,"&DATEDIF(C7,$C$3,"MD")&"Days" -> 26Years,9Months,23Days
B8: Rajeev Singh | C8: 37027 | D8: =DAY(C8) -> 16 | E8: =MONTH(C8) -> 5 | F8: =TEXT(C8,"mmmm") -> May | G8: =YEAR(C8) -> 2001 | H8: =DATEDIF(C8,$C$3,"Y") -> 25 | I8: =DATEDIF(C8,$C$3,"Y")&"Years,"&DATEDIF(C8,$C$3,"YM")&"Months,"&DATEDIF(C8,$C$3,"MD")&"Days" -> 25Years,3Months,21Days
B9: Gururaj Joshi | C9: 37946 | D9: =DAY(C9) -> 21 | E9: =MONTH(C9) -> 11 | F9: =TEXT(C9,"mmmm") -> November | G9: =YEAR(C9) -> 2003 | H9: =DATEDIF(C9,$C$3,"Y") -> 22 | I9: =DATEDIF(C9,$C$3,"Y")&"Years,"&DATEDIF(C9,$C$3,"YM")&"Months,"&DATEDIF(C9,$C$3,"MD")&"Days" -> 22Years,9Months,16Days
B10: Sudesh Pillai | C10: 38113 | D10: =DAY(C10) -> 6 | E10: =MONTH(C10) -> 5 | F10: =TEXT(C10,"mmmm") -> May | G10: =YEAR(C10) -> 2004 | H10: =DATEDIF(C10,$C$3,"Y") -> 22 | I10: =DATEDIF(C10,$C$3,"Y")&"Years,"&DATEDIF(C10,$C$3,"YM")&"Months,"&DATEDIF(C10,$C$3,"MD")&"Days" -> 22Years,4Months,0Days
B11: Yashraj Vaidya | C11: 38449 | D11: =DAY(C11) -> 7 | E11: =MONTH(C11) -> 4 | F11: =TEXT(C11,"mmmm") -> April | G11: =YEAR(C11) -> 2005 | H11: =DATEDIF(C11,$C$3,"Y") -> 21 | I11: =DATEDIF(C11,$C$3,"Y")&"Years,"&DATEDIF(C11,$C$3,"YM")&"Months,"&DATEDIF(C11,$C$3,"MD")&"Days" -> 21Years,4Months,30Days
B12: Dinesh Dhanuka | C12: 39846 | D12: =DAY(C12) -> 2 | E12: =MONTH(C12) -> 2 | F12: =TEXT(C12,"mmmm") -> February | G12: =YEAR(C12) -> 2009 | H12: =DATEDIF(C12,$C$3,"Y") -> 17 | I12: =DATEDIF(C12,$C$3,"Y")&"Years,"&DATEDIF(C12,$C$3,"YM")&"Months,"&DATEDIF(C12,$C$3,"MD")&"Days" -> 17Years,7Months,4Days
B13: Yogesh Mansharamani | C13: 40330 | D13: =DAY(C13) -> 1 | E13: =MONTH(C13) -> 6 | F13: =TEXT(C13,"mmmm") -> June | G13: =YEAR(C13) -> 2010 | H13: =DATEDIF(C13,$C$3,"Y") -> 16 | I13: =DATEDIF(C13,$C$3,"Y")&"Years,"&DATEDIF(C13,$C$3,"YM")&"Months,"&DATEDIF(C13,$C$3,"MD")&"Days" -> 16Years,3Months,5Days
B14: Ram Ambradkar | C14: 40495 | D14: =DAY(C14) -> 13 | E14: =MONTH(C14) -> 11 | F14: =TEXT(C14,"mmmm") -> November | G14: =YEAR(C14) -> 2010 | H14: =DATEDIF(C14,$C$3,"Y") -> 15 | I14: =DATEDIF(C14,$C$3,"Y")&"Years,"&DATEDIF(C14,$C$3,"YM")&"Months,"&DATEDIF(C14,$C$3,"MD")&"Days" -> 15Years,9Months,24Days
B15: Ruffina Joshi | C15: 40574 | D15: =DAY(C15) -> 31 | E15: =MONTH(C15) -> 1 | F15: =TEXT(C15,"mmmm") -> January | G15: =YEAR(C15) -> 2011 | H15: =DATEDIF(C15,$C$3,"Y") -> 15 | I15: =DATEDIF(C15,$C$3,"Y")&"Years,"&DATEDIF(C15,$C$3,"YM")&"Months,"&DATEDIF(C15,$C$3,"MD")&"Days" -> 15Years,7Months,6Days
B16: Simon Rodrigues | C16: 41400 | D16: =DAY(C16) -> 6 | E16: =MONTH(C16) -> 5 | F16: =TEXT(C16,"mmmm") -> May | G16: =YEAR(C16) -> 2013 | H16: =DATEDIF(C16,$C$3,"Y") -> 13 | I16: =DATEDIF(C16,$C$3,"Y")&"Years,"&DATEDIF(C16,$C$3,"YM")&"Months,"&DATEDIF(C16,$C$3,"MD")&"Days" -> 13Years,4Months,0Days
B17: Dhiren Sheth | C17: 42027 | D17: =DAY(C17) -> 23 | E17: =MONTH(C17) -> 1 | F17: =TEXT(C17,"mmmm") -> January | G17: =YEAR(C17) -> 2015 | H17: =DATEDIF(C17,$C$3,"Y") -> 11 | I17: =DATEDIF(C17,$C$3,"Y")&"Years,"&DATEDIF(C17,$C$3,"YM")&"Months,"&DATEDIF(C17,$C$3,"MD")&"Days" -> 11Years,7Months,14Days
B18: Ashok Samtaney | C18: 42124 | D18: =DAY(C18) -> 30 | E18: =MONTH(C18) -> 4 | F18: =TEXT(C18,"mmmm") -> April | G18: =YEAR(C18) -> 2015 | H18: =DATEDIF(C18,$C$3,"Y") -> 11 | I18: =DATEDIF(C18,$C$3,"Y")&"Years,"&DATEDIF(C18,$C$3,"YM")&"Months,"&DATEDIF(C18,$C$3,"MD")&"Days" -> 11Years,4Months,7Days

Sheet Sort
C2: Sort as per conditions and Copy paste the results, by adding a new sheet in this file. Plus Paste Screenshots of Sort Box.
C3: 1. Sort Segment, inside each segment Country should be sorted, with sorted profit for each country Low to high.(Use Custom Sort)
B5: ID | C5: Segment | D5: Country | E5: Date | F5: Profit
B6: 8 | C6: Government | D6: Mexico | E6: 44348 | F6: 108879
B7: 27 | C7: Government | D7: France | E7: 44470 | F7: 165656
B8: 33 | C8: Government | D8: France | E8: 44256 | F8: 25467
B9: 38 | C9: Government | D9: Germany | E9: 44256 | F9: 16452
B10: 46 | C10: Government | D10: France | E10: 44440 | F10: 135801
B11: 72 | C11: Government | D11: Germany | E11: 44348 | F11: 247286
B12: 84 | C12: Government | D12: United States of America | E12: 44287 | F12: 191293
B13: 88 | C13: Government | D13: Canada | E13: 44197 | F13: 36125
B14: 111 | C14: Government | D14: United States of America | E14: 44197 | F14: 123287
B15: 113 | C15: Government | D15: United States of America | E15: 44378 | F15: -34980
B16: 115 | C16: Government | D16: Germany | E16: 44317 | F16: 72086
B17: 127 | C17: Government | D17: United States of America | E17: 44470 | F17: 84660
... B318: 3498 | C318: Enterprise | D318: Germany | E318: 44409 | F318: 7269

Sheet Short ans
B3: Segment | C3: Country | D3: Profit
B4: Channel Partners | C4: Canada | D4: -14202
B5: Channel Partners | C5: Canada | D5: 17043
B6: Channel Partners | C6: Canada | D6: 55010
B7: Channel Partners | C7: Canada | D7: 60394
B8: Channel Partners | C8: Canada | D8: 166490
B9: Channel Partners | C9: Canada | D9: 196137
B10: Channel Partners | C10: Canada | D10: 219249
B11: Channel Partners | C11: Canada | D11: 232472
B12: Channel Partners | C12: France | D12: 39271
B13: Channel Partners | C13: France | D13: 60921
B14: Channel Partners | C14: France | D14: 87532
B15: Channel Partners | C15: France | D15: 89649
... B316: Small Business | C316: United States of America | D316: 248756

Sheet Filter
C2: Sort as per conditions and Copy paste the results, by adding a new sheet in this file. Plus Paste Screenshots of Text and Date filters (wherever necessary)
C3: 1. Filter all the Country name starts with letter "F"
C4: 2. Filter the data in Quarter 3
C6: ID | D6: Segment | E6: Country | F6: Date | G6: Profit
C7: 1 | D7: Government | E7: Mexico | F7: 44348 | G7: 108879
C8: 2 | D8: Government | E8: France | F8: 44470 | G8: 165656
C9: 3 | D9: Government | E9: France | F9: 44256 | G9: 25467
C10: 4 | D10: Government | E10: Germany | F10: 44256 | G10: 16452
C11: 5 | D11: Government | E11: France | F11: 44440 | G11: 135801
C12: 6 | D12: Government | E12: Germany | F12: 44348 | G12: 247286
C13: 7 | D13: Government | E13: United States of America | F13: 44287 | G13: 191293
C14: 8 | D14: Government | E14: Canada | F14: 44197 | G14: 36125
C15: 9 | D15: Government | E15: United States of America | F15: 44197 | G15: 123287
C16: 10 | D16: Government | E16: United States of America | F16: 44378 | G16: -34980
C17: 11 | D17: Government | E17: Germany | F17: 44317 | G17: 72086
C18: 12 | D18: Government | E18: United States of America | F18: 44470 | G18: 84660
... C319: 313 | D319: Enterprise | E319: Germany | F319: 44409 | G319: 7269

Sheet Filter ans
C4: Country | D4: Date
C5: Mexico | D5: 44348
C6: France | D6: 44470
C7: France | D7: 44256
C8: Germany | D8: 44256
C9: France | D9: 44440
C10: Germany | D10: 44348
C11: United States of America | D11: 44287
C12: Canada | D12: 44197
C13: United States of America | D13: 44197
C14: United States of America | D14: 44378
C15: Germany | D15: 44317
C16: United States of America | D16: 44470
... C317: Germany | D317: 44409

Sheet Charts1
C2: Create Line Chart with Proper formatting
C3: Should be formatted as shown in picture
C4: Note - Do not use Pivot Table or Pivot charts
C6: Date | D6: Revenue'000
C7: 1990 | D7: 2156
C8: 1991 | D8: 3562
C9: 1992 | D9: 7506
C10: 1993 | D10: 6258
C11: 1994 | D11: 6279
C12: 1995 | D12: 1963
C13: 1996 | D13: 6736
C14: 1997 | D14: 3280
C15: 1998 | D15: 8398
C16: 1999 | D16: 2882
C17: 2000 | D17: 4686
C18: 2001 | D18: 6976
... C21: 2004 | D21: 8418

Sheet Charts2
C2: Create Combo Chart with Proper formatting
C3: Should be formatted as shown in picture
C4: Note - Do not use Pivot Table or Pivot charts
C6: Date | D6: Revenue'000 | E6: Running Total | F6: %
C7: 2005 | D7: 528
C8: 2006 | D8: 4550 | E8: =SUM($D$6:D8) -> 5078 | F8: =E8/$E$24 -> 0.065615713
C9: 2007 | D9: 8189 | E9: =SUM($D$6:D9) -> 13267 | F9: =E9/$E$24 -> 0.17143042
C10: 2008 | D10: 1730 | E10: =SUM($D$6:D10) -> 14997 | F10: =E10/$E$24 -> 0.19378473
C11: 2009 | D11: 5262 | E11: =SUM($D$6:D11) -> 20259 | F11: =E11/$E$24 -> 0.26177801
C12: 2010 | D12: 2172 | E12: =SUM($D$6:D12) -> 22431 | F12: =E12/$E$24 -> 0.28984365
C13: 2011 | D13: 4384 | E13: =SUM($D$6:D13) -> 26815 | F13: =E13/$E$24 -> 0.34649179
C14: 2012 | D14: 8709 | E14: =SUM($D$6:D14) -> 35524 | F14: =E14/$E$24 -> 0.45902571
C15: 2013 | D15: 3618 | E15: =SUM($D$6:D15) -> 39142 | F15: =E15/$E$24 -> 0.50577594
C16: 2014 | D16: 6372 | E16: =SUM($D$6:D16) -> 45514 | F16: =E16/$E$24 -> 0.58811216
C17: 2015 | D17: 3456 | E17: =SUM($D$6:D17) -> 48970 | F17: =E17/$E$24 -> 0.63276909
C18: 2016 | D18: 7478 | E18: =SUM($D$6:D18) -> 56448 | F18: =E18/$E$24 -> 0.72939656
C19: 2017 | D19: 4649 | E19: =SUM($D$6:D19) -> 61097 | F19: =E19/$E$24 -> 0.78946892
... C24: 2022 | D24: 3490 | E24: =SUM($D$6:D24) -> 77390 | F24: =E24/$E$24 -> 1
C25: Total | D25: =SUM(D7:D24) -> 77390
